package_name/__init__.py
package_name/module1_name/__init__.py
package_name/module1_name/file1_name.py
package_name/module1_name/file2_name.py
package_name/module2_name/__init__.py
package_name/module2_name/file1_name.py
package_name/module2_name/file2_name.py
Processing_of_image_package-0.0.1.dist-info/METADATA
Processing_of_image_package-0.0.1.dist-info/WHEEL
Processing_of_image_package-0.0.1.dist-info/top_level.txt
Processing_of_image_package-0.0.1.dist-info/RECORD
