Metadata-Version: 2.1
Name: Processing-of-image-package
Version: 0.0.1
Summary: Python package template with multiple modules
Home-page: https://github.com/Ray-King11/Processing-of-image-package
Author: Ray_King
Author-email: raytoyagami25@gmail.com
Requires-Python: >=3.6
Requires-Dist: Pillow
Requires-Dist: opencv-python
Requires-Dist: scikit-image
